scrubadub_spacy/__init__.py
scrubadub_spacy/detectors/__init__.py
scrubadub_spacy/detectors/spacy.py
scrubadub_spacy/detectors/spacy_name_title.py
scrubadub_spacy-2.0.0.dist-info/LICENSE
scrubadub_spacy-2.0.0.dist-info/METADATA
scrubadub_spacy-2.0.0.dist-info/WHEEL
scrubadub_spacy-2.0.0.dist-info/entry_points.txt
scrubadub_spacy-2.0.0.dist-info/top_level.txt
scrubadub_spacy-2.0.0.dist-info/RECORD
