Metadata-Version: 2.1
Name: scrubadub-spacy
Version: 2.0.0
Summary: Use Spacy NER models to clean personally identifiable information from dirty dirty text.
Home-page: https://github.com/LeapBeyond/scrubadub_spacy
Author: Thomas Bird
Author-email: thomas.bird@leapbeyond.ai
License: MIT
Download-URL: https://github.com/LeapBeyond/scrubadub_spacy/archives/master
Platform: UNKNOWN
Classifier: Intended Audience :: Developers
Classifier: Development Status :: 5 - Production/Stable
Classifier: License :: OSI Approved :: Apache Software License
Classifier: Natural Language :: English
Classifier: Programming Language :: Python
Classifier: Programming Language :: Python :: 3
Classifier: Programming Language :: Python :: 3.6
Classifier: Programming Language :: Python :: 3.7
Classifier: Programming Language :: Python :: 3.8
Classifier: Programming Language :: Python :: 3.9
Classifier: Topic :: Software Development :: Libraries
Classifier: Topic :: Scientific/Engineering :: Information Analysis
Classifier: Topic :: Text Processing
Classifier: Topic :: Utilities
License-File: LICENSE
Requires-Dist: scrubadub (>=2.0.0rc0)
Requires-Dist: wheel
Requires-Dist: spacy[transformers] (>=3.0.0) ; python_version >= "3.6"
